grams/__init__.py
grams/__main__.py
grams/algorithm/__init__.py
grams/algorithm/candidate_graph/__init__.py
grams/algorithm/candidate_graph/cg_factory.py
grams/algorithm/candidate_graph/cg_graph.py
grams/algorithm/data_graph/__init__.py
grams/algorithm/data_graph/dg_config.py
grams/algorithm/data_graph/dg_factory.py
grams/algorithm/data_graph/dg_graph.py
grams/algorithm/data_graph/dg_inference.py
grams/algorithm/data_graph/dg_pruning.py
grams/algorithm/deprecated/__init__.py
grams/algorithm/deprecated/bank_solver.py
grams/algorithm/deprecated/link_feature.py
grams/algorithm/deprecated/psl_solver.py
grams/algorithm/deprecated/semantic_graph.py.deprecated
grams/algorithm/deprecated/type_feature.py
grams/algorithm/helpers.py
grams/algorithm/inferences/__init__.py
grams/algorithm/inferences/features/__init__.py
grams/algorithm/inferences/features/rel_feature.py
grams/algorithm/inferences/features/rel_feature2.py
grams/algorithm/inferences/features/string_similarity.py
grams/algorithm/inferences/features/structure_feature.py
grams/algorithm/inferences/features/structure_feature2.py
grams/algorithm/inferences/features/tree_utils.py
grams/algorithm/inferences/features/type_feature.py
grams/algorithm/inferences/features/type_feature_config.py
grams/algorithm/inferences/psl_gram_model.py
grams/algorithm/inferences/psl_gram_model_exp.py
grams/algorithm/inferences/psl_gram_model_exp2.py
grams/algorithm/inferences/psl_lib.py
grams/algorithm/kg_index.py
grams/algorithm/literal_matchers/__init__.py
grams/algorithm/literal_matchers/coordinate_match.py
grams/algorithm/literal_matchers/datetime_match.py
grams/algorithm/literal_matchers/entity_match.py
grams/algorithm/literal_matchers/literal_match.py
grams/algorithm/literal_matchers/number_match.py
grams/algorithm/literal_matchers/string_match.py
grams/algorithm/literal_matchers/text_parser.py
grams/algorithm/literal_matchers/types.py
grams/algorithm/postprocessing/__init__.py
grams/algorithm/postprocessing/arborescence.py
sm_grams-2.1.7.dist-info/entry_points.txt
sm_grams-2.1.7.dist-info/LICENSE
sm_grams-2.1.7.dist-info/WHEEL
sm_grams-2.1.7.dist-info/METADATA
sm_grams-2.1.7.dist-info/RECORD
