Metadata-Version: 2.1
Name: sm-grams
Version: 2.1.7
Summary: 
Home-page: https://github.com/usc-isi-i2/grams
License: MIT
Author: Binh Vu
Author-email: binh@toan2.com
Requires-Python: >=3.8,<4.0
Classifier: License :: OSI Approved :: MIT License
Classifier: Programming Language :: Python :: 3
Classifier: Programming Language :: Python :: 3.8
Classifier: Programming Language :: Python :: 3.9
Classifier: Programming Language :: Python :: 3.10
Classifier: Programming Language :: Python :: 3.11
Requires-Dist: beautifulsoup4 (>=4.9.3,<5.0.0)
Requires-Dist: click (>=8.0.0,<=8.0.4)
Requires-Dist: fastnumbers (>=3.2.1,<4.0.0)
Requires-Dist: ftfy (>=6.1.1,<7.0.0)
Requires-Dist: graph-wrapper (>=1.5.0,<2.0.0)
Requires-Dist: html5lib (>=1.1,<2.0)
Requires-Dist: hugedict (>=2.7.1,<3.0.0)
Requires-Dist: ipython (>=8.0.1,<9.0.0)
Requires-Dist: kgdata (>=3.2.0,<4.0.0)
Requires-Dist: loguru (>=0.6.0,<0.7.0)
Requires-Dist: matplotlib (>=3.5.3,<4.0.0)
Requires-Dist: ned (>=1.0.0,<2.0.0)
Requires-Dist: networkx (>=2.8.2,<3.0.0)
Requires-Dist: numparser2 (>=1.0.0,<2.0.0)
Requires-Dist: omegaconf (>=2.0.6,<3.0.0)
Requires-Dist: orjson (>=3.8.0,<4.0.0)
Requires-Dist: pslpython (==2.2.2)
Requires-Dist: python-slugify (>=6.1.2,<7.0.0)
Requires-Dist: rdflib (>=6.1.1,<7.0.0)
Requires-Dist: requests (>=2.28.0,<3.0.0)
Requires-Dist: rltk (==2.0.0a20)
Requires-Dist: ruamel.yaml (>=0.17.21,<0.18.0)
Requires-Dist: sem-desc (>=3.9.0,<4.0.0)
Requires-Dist: steiner-tree (>=1.1.3,<2.0.0)
Requires-Dist: tqdm (>=4.64.0,<5.0.0)
Requires-Dist: typing_extensions (>=4.0.0,<5.0.0)
Requires-Dist: ujson (>=5.5.0,<6.0.0)
Project-URL: Repository, https://github.com/usc-isi-i2/grams
